{
  "created_at": "2025-05-17T13:21:16.235Z",
  "description": "",
  "end_time": "2025-05-17T13:21:15+00:00",
  "exercises": [
    {
      "exercise_template_id": "927a2231-9678-4d77-a58d-2dfe25f3ca8f",
      "index": 0,
      "notes": "",
      "sets": [
        {
          "custom_metric": null,
          "distance_meters": null,
          "duration_seconds": null,
          "index": 0,
          "reps": 5,
          "rpe": null,
          "type": "warmup",
          "weight_kg": 142.88176647222653
        },
        {
          "custom_metric": null,
          "distance_meters": null,
          "duration_seconds": null,
          "index": 1,
          "reps": 4,
          "rpe": 7,
          "type": "normal",
          "weight_kg": 165.5614119440085
        },
        {
          "custom_metric": null,
          "distance_meters": null,
          "duration_seconds": null,
          "index": 2,
          "reps": 4,
          "rpe": 7,
          "type": "normal",
          "weight_kg": 165.5614119440085
        },
        {
          "custom_metric": null,
          "distance_meters": null,
          "duration_seconds": null,
          "index": 3,
          "reps": 4,
          "rpe": 8,
          "type": "normal",
          "weight_kg": 165.5614119440085
        }
      ],
      "superset_id": null,
      "title": "3-0-0 Tempo Low Bar Squat"
    },
    {
      "exercise_template_id": "79D0BB3A",
      "index": 1,
      "notes": "",
      "sets": [
        {
          "custom_metric": null,
          "distance_meters": null,
          "duration_seconds": null,
          "index": 0,
          "reps": 3,
          "rpe": null,
          "type": "warmup",
          "weight_kg": 83.91468824559335
        },
        {
          "custom_metric": null,
          "distance_meters": null,
          "duration_seconds": null,
          "index": 1,
          "reps": 2,
          "rpe": null,
          "type": "warmup",
          "weight_kg": 106.59433371737533
        },
        {
          "custom_metric": null,
          "distance_meters": null,
          "duration_seconds": null,
          "index": 2,
          "reps": 1,
          "rpe": null,
          "type": "warmup",
          "weight_kg": 115.66619190608813
        },
        {
          "custom_metric": null,
          "distance_meters": null,
          "duration_seconds": null,
          "index": 3,
          "reps": 1,
          "rpe": 7,
          "type": "normal",
          "weight_kg": 120.20212100044454
        },
        {
          "custom_metric": null,
          "distance_meters": null,
          "duration_seconds": null,
          "index": 4,
          "reps": 1,
          "rpe": 7.5,
          "type": "normal",
          "weight_kg": 124.73805009480093
        },
        {
          "custom_metric": null,
          "distance_meters": null,
          "duration_seconds": null,
          "index": 5,
          "reps": 5,
          "rpe": null,
          "type": "normal",
          "weight_kg": 97.52247552866254
        },
        {
          "custom_metric": null,
          "distance_meters": null,
          "duration_seconds": null,
          "index": 6,
          "reps": 5,
          "rpe": null,
          "type": "normal",
          "weight_kg": 97.52247552866254
        }
      ],
      "superset_id": null,
      "title": "Bench Press (Barbell)"
    },
    {
      "exercise_template_id": "6A6C31A5",
      "index": 2,
      "notes": "",
      "sets": [
        {
          "custom_metric": null,
          "distance_meters": null,
          "duration_seconds": null,
          "index": 0,
          "reps": 10,
          "rpe": null,
          "type": "normal",
          "weight_kg": 65.77097186816776
        }
      ],
      "superset_id": null,
      "title": "Lat Pulldown (Cable)"
    }
  ],
  "id": "8de467dd-8f2a-4035-88be-d93b7f3387e7",
  "routine_id": "2977dae5-017d-43b9-8102-612e05b683f5",
  "start_time": "2025-05-17T12:23:12+00:00",
  "title": "Day 4 (BENCH)",
  "updated_at": "2025-05-17T13:21:16.235Z"
}